bkyml/__init__.py
bkyml/skeleton.py
bkyml-1.4.3.dist-info/AUTHORS.rst
bkyml-1.4.3.dist-info/LICENSE.txt
bkyml-1.4.3.dist-info/METADATA
bkyml-1.4.3.dist-info/WHEEL
bkyml-1.4.3.dist-info/entry_points.txt
bkyml-1.4.3.dist-info/top_level.txt
bkyml-1.4.3.dist-info/RECORD
