Metadata-Version: 2.1
Name: bkyml
Version: 1.4.3
Summary: CLI tool to generate Buildkite pipeline YAML
Home-page: http://github.com/joscha/bkyml
Author: Joscha Feth
Author-email: joscha@feth.com
License: mit
Platform: any
Classifier: Development Status :: 5 - Production/Stable
Classifier: Programming Language :: Python
Requires-Dist: ruamel.yaml
